kinto_wizard/__init__.py
kinto_wizard/__main__.py
kinto_wizard/kinto2yaml.py
kinto_wizard/logger.py
kinto_wizard/validate.py
kinto_wizard/yaml2kinto.py
kinto_wizard-6.0.1.dist-info/licenses/LICENSE
kinto_wizard-6.0.1.dist-info/METADATA
kinto_wizard-6.0.1.dist-info/WHEEL
kinto_wizard-6.0.1.dist-info/entry_points.txt
kinto_wizard-6.0.1.dist-info/top_level.txt
kinto_wizard-6.0.1.dist-info/RECORD
