Metadata-Version: 2.4
Name: kinto-wizard
Version: 6.0.1
Summary: kinto-wizard is a tool to configure a kinto server from an YAML file.
Author-email: Mozilla Services <developers@kinto-storage.org>
License: Copyright 2012 - Mozilla Foundation
Project-URL: Repository, https://github.com/Kinto/kinto-wizard
Keywords: web services
Classifier: Programming Language :: Python
Classifier: Programming Language :: Python :: 3
Classifier: Programming Language :: Python :: Implementation :: CPython
Classifier: Topic :: Internet :: WWW/HTTP
Classifier: Topic :: Internet :: WWW/HTTP :: WSGI :: Application
Classifier: License :: OSI Approved :: Apache Software License
License-File: LICENSE
Requires-Dist: jsonschema
Requires-Dist: kinto-http>=11.9
Requires-Dist: ruamel.yaml>0.15
Provides-Extra: dev
Requires-Dist: kinto; extra == "dev"
Requires-Dist: ruff; extra == "dev"
Requires-Dist: pytest; extra == "dev"
Requires-Dist: pytest-cache; extra == "dev"
Requires-Dist: pytest-cov; extra == "dev"
Requires-Dist: pytest-xdist; extra == "dev"
Dynamic: license-file
